LICENSE
MANIFEST.in
README.md
setup.cfg
setup.py
cftw/__init__.py
cftw/logger.py
cftw/utils.py
cftw/version.py
cftw.egg-info/PKG-INFO
cftw.egg-info/SOURCES.txt
cftw.egg-info/dependency_links.txt
cftw.egg-info/entry_points.txt
cftw.egg-info/requires.txt
cftw.egg-info/top_level.txt
cftw/bases/__init__.py
cftw/bases/client.py
cftw/bases/init.py
cftw/bases/template.py
cftw/bases/templates/bases/continuumio-anaconda3/.travis.yml
cftw/bases/templates/bases/continuumio-anaconda3/README.md
cftw/bases/templates/bases/continuumio-anaconda3/Singularity
cftw/bases/templates/bases/continuumio-anaconda3/analysis/README.md
cftw/bases/templates/bases/continuumio-anaconda3/analysis/main.py
cftw/bases/templates/bases/continuumio-anaconda3/analysis/metrics.py
cftw/bases/templates/bases/continuumio-anaconda3/analysis/helpers/README.md
cftw/bases/templates/bases/continuumio-anaconda3/analysis/helpers/data.py
cftw/bases/templates/bases/continuumio-anaconda3/analysis/helpers/logger.py
cftw/bases/templates/bases/continuumio-anaconda3/analysis/helpers/results.py
cftw/bases/templates/bases/continuumio-anaconda3/analysis/helpers/utils.py
cftw/bases/templates/bases/continuumio-anaconda3/analysis/tests/README.md
cftw/bases/templates/bases/continuumio-anaconda3/analysis/tests/__init__.py
cftw/bases/templates/bases/continuumio-anaconda3/analysis/tests/test_submission.py
cftw/bases/templates/bases/continuumio-anaconda3/data/input/README.md
cftw/bases/templates/bases/continuumio-anaconda3/data/mnt/README.md
cftw/bases/templates/bases/continuumio-anaconda3/img/containers-ftw.png
cftw/bases/templates/bases/ubuntu16.04-python2/.travis.yml
cftw/bases/templates/bases/ubuntu16.04-python2/README.md
cftw/bases/templates/bases/ubuntu16.04-python2/Singularity
cftw/bases/templates/bases/ubuntu16.04-python2/analysis/README.md
cftw/bases/templates/bases/ubuntu16.04-python2/analysis/main.py
cftw/bases/templates/bases/ubuntu16.04-python2/analysis/metrics.py
cftw/bases/templates/bases/ubuntu16.04-python2/analysis/helpers/README.md
cftw/bases/templates/bases/ubuntu16.04-python2/analysis/helpers/data.py
cftw/bases/templates/bases/ubuntu16.04-python2/analysis/helpers/logger.py
